

        [
	{
		"codigoTipoComprobante": "FAC",
		"numeroComprobante": "B0000300002139",
		"codigoTalonario": "5",
		"codigoCliente": "108865",
		"codigoCondicionDeVenta": 1,
		"numeroDeProyecto": "",
		"codigoOperacionRG3685": "00001",
		"codigoClasificacion": "",
		"fechaComprobante": "2026-03-18 00:00:00.000",
		"fechaCierreTesoreria": "2026-03-18 00:00:00.000",
		"codigoListaPrecio": 1,
		"cotizacionVentas": null,
		"codigoContracuenta": "20",
		"codigoDeposito": "1",
		"codigoVendedor": "164",
		"idMotivo": "3",
		"codigoAsiento": "1",
		"leyenda1": "",
		"leyenda2": "",
		"leyenda3": "",
		"leyenda4": "",
		"leyenda5": "",
		"esMonedaExtranjera": false,
		"total" : 56690.08,
		"totalExento": 0.00,
		"totalIva": 9838.77,
		"subtotal": 56690.08,
		"totalSinImpuestos": 46851.31,
		"subtotalSinImpuestos": 46851.31,
		"descuentoPorcentaje": 0,
		"descuentoMonto": 0,
		"descuentoMontoSinIva": 0,
		"recargoPorcentaje": 0,
		"recargoMonto": 0,
		"recargoMontoSinIva": 0,
		"recargoFletePorcentaje": 0,
		"recargoFleteMonto": 0,
		"recargoFleteMontoSinIva": 0,
		"interesesPorcentaje": 0.00,
		"interesesMontoSinIva": 0.00,
		"observaciones": "",
		"rg3668TipoIdentificacionFirmante": null,
		"rg3668CaracterDelFirmante": null,
		"rg3668CodigoIdentificacionFirmante": "",
		"rg3668MotivoDeExcepcion": null,
		"rg3668CodigoWeb": "666",
		"items": [
                {
				                        "codigo": "400277",
				                        "descripcion": "LIMPIA VIDRIOS BAUTI S/E COLOR5/400277-1",
                                        "descripcionAdicional": "5/400277-1",
				                        "descargaStock" : false,
				                        "cantidad": 1,
                                        "importeIva": 520.49,
				                        "codigoDeposito": "1",
				                        "codigoUM": "UNI",
				                        "precio": 2999.00,
                                        "importe": 2999.00,
                                         "importeSinImpuestos": 2478.51
                        	}
                     ,{
				                        "codigo": "101405",
				                        "descripcion": "SPLASH HUMECT. B.LOVE COCONUT 5/101405-0",
                                        "descripcionAdicional": "5/101405-0",
				                        "descargaStock" : false,
				                        "cantidad": 1,
                                        "importeIva": 1318.83,
				                        "codigoDeposito": "1",
				                        "codigoUM": "UNI",
				                        "precio": 7599.00,
                                        "importe": 7599.00,
                                         "importeSinImpuestos": 6280.17
                        	}
                     ,{
				                        "codigo": "100459",
				                        "descripcion": "LOCION COLONIA FEMENINA ADDICT1/100459-1",
                                        "descripcionAdicional": "1/100459-1",
				                        "descargaStock" : false,
				                        "cantidad": 1,
                                        "importeIva": 1214.70,
				                        "codigoDeposito": "1",
				                        "codigoUM": "UNI",
				                        "precio": 6999.00,
                                        "importe": 6999.00,
                                         "importeSinImpuestos": 5784.30
                        	}
                     ,{
				                        "codigo": "101404",
				                        "descripcion": "EAU TOILETTE MASC. SEX MEN BLA1/101404-8",
                                        "descripcionAdicional": "1/101404-8",
				                        "descargaStock" : false,
				                        "cantidad": 1,
                                        "importeIva": 2603.13,
				                        "codigoDeposito": "1",
				                        "codigoUM": "UNI",
				                        "precio": 14999.00,
                                        "importe": 14999.00,
                                         "importeSinImpuestos": 12395.87
                        	}
                     ,{
				                        "codigo": "101576",
				                        "descripcion": "PROT.SOLAR COLOR DERMAT FPS60 1/101576-2",
                                        "descripcionAdicional": "1/101576-2",
				                        "descargaStock" : false,
				                        "cantidad": 1,
                                        "importeIva": 3470.90,
				                        "codigoDeposito": "1",
				                        "codigoUM": "UNI",
				                        "precio": 19999.00,
                                        "importe": 19999.00,
                                         "importeSinImpuestos": 16528.10
                        	}
                     ,{
				                        "codigo": "8264",
				                        "descripcion": "BUENASNOTICIAS-CAMP.154/8264-3",
                                        "descripcionAdicional": "4/8264-3",
				                        "descargaStock" : false,
				                        "cantidad": 1,
                                        "importeIva": 0.00,
				                        "codigoDeposito": "1",
				                        "codigoUM": "UNI",
				                        "precio": 0.01,
                                        "importe": 0.01,
                                         "importeSinImpuestos": 0.01
                        	}
                     ,{
				                        "codigo": "101405",
				                        "descripcion": "SPLASH HUMECT. B.LOVE COCONUT 4/101405-0",
                                        "descripcionAdicional": "4/101405-0",
				                        "descargaStock" : false,
				                        "cantidad": 3,
                                        "importeIva": 0.01,
				                        "codigoDeposito": "1",
				                        "codigoUM": "UNI",
				                        "precio": 0.01,
                                        "importe": 0.03,
                                         "importeSinImpuestos": 0.02
                        	}
                     ,{
				                        "codigo": "101405",
				                        "descripcion": "SPLASH HUMECT. B.LOVE COCONUT 5/101405-0",
                                        "descripcionAdicional": "5/101405-0",
				                        "descargaStock" : false,
				                        "cantidad": 1,
                                        "importeIva": 451.07,
				                        "codigoDeposito": "1",
				                        "codigoUM": "UNI",
				                        "precio": 2599.00,
                                        "importe": 2599.00,
                                         "importeSinImpuestos": 2147.93
                        	}
                     ,{
				                        "codigo": "101405",
				                        "descripcion": "SPLASH HUMECT. B.LOVE COCONUT 5/101405-0",
                                        "descripcionAdicional": "5/101405-0",
				                        "descargaStock" : false,
				                        "cantidad": 2,
                                        "importeIva": 1040.98,
				                        "codigoDeposito": "1",
				                        "codigoUM": "UNI",
				                        "precio": 2999.00,
                                        "importe": 5998.00,
                                         "importeSinImpuestos": 4957.02
                        	}
                     ,{
				                        "codigo": "8265",
				                        "descripcion": "BUENASNOTICIAS-CAMP.164/8265-5",
                                        "descripcionAdicional": "4/8265-5",
				                        "descargaStock" : false,
				                        "cantidad": 1,
                                        "importeIva": 0.00,
				                        "codigoDeposito": "1",
				                        "codigoUM": "UNI",
				                        "precio": 0.01,
                                        "importe": 0.01,
                                         "importeSinImpuestos": 0.01
                        	}
                     ,{
				                        "codigo": "101405",
				                        "descripcion": "SPLASH HUMECT. B.LOVE COCONUT 5/101405-0",
                                        "descripcionAdicional": "5/101405-0",
				                        "descargaStock" : false,
				                        "cantidad": 1,
                                        "importeIva": 346.93,
				                        "codigoDeposito": "1",
				                        "codigoUM": "UNI",
				                        "precio": 1999.00,
                                        "importe": 1999.00,
                                         "importeSinImpuestos": 1652.07
                        	}
                     ,{
				                        "codigo": "101405",
				                        "descripcion": "SPLASH HUMECT. B.LOVE COCONUT 5/101405-0",
                                        "descripcionAdicional": "5/101405-0",
				                        "descargaStock" : false,
				                        "cantidad": 2,
                                        "importeIva": 867.42,
				                        "codigoDeposito": "1",
				                        "codigoUM": "UNI",
				                        "precio": 2499.00,
                                        "importe": 4998.00,
                                         "importeSinImpuestos": 4130.58
                        	}
                     ,{
				                        "codigo": "101405",
				                        "descripcion": "SPLASH HUMECT. B.LOVE COCONUT 5/101405-0",
                                        "descripcionAdicional": "5/101405-0",
				                        "descargaStock" : false,
				                        "cantidad": 1,
                                        "importeIva": 694.04,
				                        "codigoDeposito": "1",
				                        "codigoUM": "UNI",
				                        "precio": 3999.00,
                                        "importe": 3999.00,
                                         "importeSinImpuestos": 3304.96
                        	}
                     ,{
	"codigo": "03",
	"descripcion": "Bonificacion Cosméticos",
	"descargaStock" : false,
	"cantidad": -1,
	"codigoDeposito": "1",
        "importeIva": -2186.62,
	"codigoUM": "BON",
	"precio": 12599.10,
        "importe": 12599.10,
        "importeSinImpuestos": -10412.48
        },{
				"codigo": "04",
				"descripcion": "Bonificación Practicosas",
				"descargaStock" : false,
				"cantidad": -1,
				"codigoDeposito": "1",
                                "importeIva": -785.96,
				"codigoUM": "BON",
				"precio": 4528.65,
                                "importe": 4528.65,
                                "importeSinImpuestos": -3742.69
                        	},
                                
                     {
				"codigo": "02",
				"descripcion": "Gastos administrativos",
				"descargaStock" : false,
				"cantidad": 1,
				"codigoDeposito": "1",
                                "importeIva": 282.85,
				"codigoUM": "UNI",
				"precio": 1629.78,
                                "importe": 1629.78,
                                "importeSinImpuestos": 1346.93
                        	}
                     
		],
		"cuotasCuentaCorriente" :
		[
			{
				"fechaVencimiento": "2026-03-18 00:00:00.000",
				"importe" : 56690.08
			}
                        ]
            }
        ]