

        [
	{
		"codigoTipoComprobante": "FAC",
		"numeroComprobante": "B0000300000429",
		"codigoTalonario": "5",
		"codigoCliente": "38992",
		"codigoCondicionDeVenta": 1,
		"numeroDeProyecto": "",
		"codigoOperacionRG3685": "00001",
		"codigoClasificacion": "",
		"fechaComprobante": "2026-03-18 00:00:00.000",
		"fechaCierreTesoreria": "2026-03-18 00:00:00.000",
		"codigoListaPrecio": 1,
		"cotizacionVentas": null,
		"codigoContracuenta": "20",
		"codigoDeposito": "1",
		"codigoVendedor": "070",
		"idMotivo": "3",
		"codigoAsiento": "1",
		"leyenda1": "24,322.95",
		"leyenda2": "111,930.00",
		"leyenda3": "",
		"leyenda4": "",
		"leyenda5": "",
		"esMonedaExtranjera": false,
		"total" : 153014.02,
		"totalExento": 0.00,
		"totalIva": 37726.08,
		"subtotal": 135435.29,
		"totalSinImpuestos": 111930.00,
		"subtotalSinImpuestos": 111930.00,
		"descuentoPorcentaje": 0,
		"descuentoMonto": 0,
		"descuentoMontoSinIva": 0,
		"recargoPorcentaje": 0,
		"recargoMonto": 0,
		"recargoMontoSinIva": 0,
		"recargoFletePorcentaje": 0,
		"recargoFleteMonto": 0,
		"recargoFleteMontoSinIva": 0,
		"interesesPorcentaje": 0.00,
		"interesesMontoSinIva": 0.00,
		"observaciones": "",
		"rg3668TipoIdentificacionFirmante": null,
		"rg3668CaracterDelFirmante": null,
		"rg3668CodigoIdentificacionFirmante": "",
		"rg3668MotivoDeExcepcion": null,
		"rg3668CodigoWeb": "666",
		"items": [
                {
				                        "codigo": "404613",
				                        "descripcion": "COMEDEROPEZS/ECOLOR5/404613-2",
                                        "descripcionAdicional": "5/404613-2",
				                        "descargaStock" : false,
				                        "cantidad": 1,
                                        "importeIva": 520.49,
				                        "codigoDeposito": "1",
				                        "codigoUM": "UNI",
				                        "precio": 2999.00,
                                        "importe": 2999.00,
                                         "importeSinImpuestos": 2478.51,
                           "percepciones":
                                        [{
						"codigoAlicuota": 11,
						"codigoPercepcion": "",
						"porcentaje": 10.50,
						"base": 2999.00,
						"importe": 314.90
					} ,{
						"codigoAlicuota": 73,
						"codigoPercepcion": "",
						"porcentaje": 3.00,
						"base": 2478.51,
						"importe": 74.36
                                        	}
                                	]
                        	}
                     ,{
				                        "codigo": "101061",
				                        "descripcion": "DELINEADOR P/OJOS 18CM 01 NEGR1/101061-2",
                                        "descripcionAdicional": "1/101061-2",
				                        "descargaStock" : false,
				                        "cantidad": 2,
                                        "importeIva": 902.13,
				                        "codigoDeposito": "1",
				                        "codigoUM": "UNI",
				                        "precio": 2599.00,
                                        "importe": 5198.00,
                                         "importeSinImpuestos": 4295.87,
                           "percepciones":
                                        [{
						"codigoAlicuota": 11,
						"codigoPercepcion": "",
						"porcentaje": 10.50,
						"base": 5198.00,
						"importe": 545.79
					} ,{
						"codigoAlicuota": 73,
						"codigoPercepcion": "",
						"porcentaje": 3.00,
						"base": 4295.87,
						"importe": 128.88
                                        	}
                                	]
                        	}
                     ,{
				                        "codigo": "42205",
				                        "descripcion": "DEO COLONIA MASC. SEX FOR MEN 1/42205-7",
                                        "descripcionAdicional": "1/42205-7",
				                        "descargaStock" : false,
				                        "cantidad": 4,
                                        "importeIva": 3470.38,
				                        "codigoDeposito": "1",
				                        "codigoUM": "UNI",
				                        "precio": 4999.00,
                                        "importe": 19996.00,
                                         "importeSinImpuestos": 16525.62,
                           "percepciones":
                                        [{
						"codigoAlicuota": 11,
						"codigoPercepcion": "",
						"porcentaje": 10.50,
						"base": 19996.00,
						"importe": 2099.58
					} ,{
						"codigoAlicuota": 73,
						"codigoPercepcion": "",
						"porcentaje": 3.00,
						"base": 16525.62,
						"importe": 495.77
                                        	}
                                	]
                        	}
                     ,{
				                        "codigo": "101063",
				                        "descripcion": "DELINEADOR P/OJOS 18CM 03 AZUL1/101063-7",
                                        "descripcionAdicional": "1/101063-7",
				                        "descargaStock" : false,
				                        "cantidad": 1,
                                        "importeIva": 451.07,
				                        "codigoDeposito": "1",
				                        "codigoUM": "UNI",
				                        "precio": 2599.00,
                                        "importe": 2599.00,
                                         "importeSinImpuestos": 2147.93,
                           "percepciones":
                                        [{
						"codigoAlicuota": 11,
						"codigoPercepcion": "",
						"porcentaje": 10.50,
						"base": 2599.00,
						"importe": 272.90
					} ,{
						"codigoAlicuota": 73,
						"codigoPercepcion": "",
						"porcentaje": 3.00,
						"base": 2147.93,
						"importe": 64.44
                                        	}
                                	]
                        	}
                     ,{
				                        "codigo": "101123",
				                        "descripcion": "CR.ROSTRO PIEL SECA/SENSIBLE A1/101123-8",
                                        "descripcionAdicional": "1/101123-8",
				                        "descargaStock" : false,
				                        "cantidad": 1,
                                        "importeIva": 1561.81,
				                        "codigoDeposito": "1",
				                        "codigoUM": "UNI",
				                        "precio": 8999.00,
                                        "importe": 8999.00,
                                         "importeSinImpuestos": 7437.19,
                           "percepciones":
                                        [{
						"codigoAlicuota": 11,
						"codigoPercepcion": "",
						"porcentaje": 10.50,
						"base": 8999.00,
						"importe": 944.90
					} ,{
						"codigoAlicuota": 73,
						"codigoPercepcion": "",
						"porcentaje": 3.00,
						"base": 7437.19,
						"importe": 223.12
                                        	}
                                	]
                        	}
                     ,{
				                        "codigo": "101025",
				                        "descripcion": "LABIAL LIQUIDO 12H SK LL 1 BEN2/101025-4",
                                        "descripcionAdicional": "2/101025-4",
				                        "descargaStock" : false,
				                        "cantidad": 3,
                                        "importeIva": 5206.09,
				                        "codigoDeposito": "1",
				                        "codigoUM": "UNI",
				                        "precio": 9999.00,
                                        "importe": 29997.00,
                                         "importeSinImpuestos": 24790.91,
                           "percepciones":
                                        [{
						"codigoAlicuota": 11,
						"codigoPercepcion": "",
						"porcentaje": 10.50,
						"base": 29997.00,
						"importe": 3149.69
					} ,{
						"codigoAlicuota": 73,
						"codigoPercepcion": "",
						"porcentaje": 3.00,
						"base": 24790.91,
						"importe": 743.73
                                        	}
                                	]
                        	}
                     ,{
				                        "codigo": "100293",
				                        "descripcion": "DEO COLONIA MASC. SEX MEN INTE1/100293-8",
                                        "descripcionAdicional": "1/100293-8",
				                        "descargaStock" : false,
				                        "cantidad": 1,
                                        "importeIva": 867.59,
				                        "codigoDeposito": "1",
				                        "codigoUM": "UNI",
				                        "precio": 4999.00,
                                        "importe": 4999.00,
                                         "importeSinImpuestos": 4131.40,
                           "percepciones":
                                        [{
						"codigoAlicuota": 11,
						"codigoPercepcion": "",
						"porcentaje": 10.50,
						"base": 4999.00,
						"importe": 524.90
					} ,{
						"codigoAlicuota": 73,
						"codigoPercepcion": "",
						"porcentaje": 3.00,
						"base": 4131.40,
						"importe": 123.94
                                        	}
                                	]
                        	}
                     ,{
				                        "codigo": "21425",
				                        "descripcion": "ESMALTE GEL SK LL 4 ROJO PASIO1/21425-9",
                                        "descripcionAdicional": "1/21425-9",
				                        "descargaStock" : false,
				                        "cantidad": 1,
                                        "importeIva": 954.37,
				                        "codigoDeposito": "1",
				                        "codigoUM": "UNI",
				                        "precio": 5499.00,
                                        "importe": 5499.00,
                                         "importeSinImpuestos": 4544.63,
                           "percepciones":
                                        [{
						"codigoAlicuota": 11,
						"codigoPercepcion": "",
						"porcentaje": 10.50,
						"base": 5499.00,
						"importe": 577.40
					} ,{
						"codigoAlicuota": 73,
						"codigoPercepcion": "",
						"porcentaje": 3.00,
						"base": 4544.63,
						"importe": 136.34
                                        	}
                                	]
                        	}
                     ,{
				                        "codigo": "101339",
				                        "descripcion": "LABIAL LIQUIDO 12H SK LL 11 NU2/101339-3",
                                        "descripcionAdicional": "2/101339-3",
				                        "descargaStock" : false,
				                        "cantidad": 1,
                                        "importeIva": 1735.36,
				                        "codigoDeposito": "1",
				                        "codigoUM": "UNI",
				                        "precio": 9999.00,
                                        "importe": 9999.00,
                                         "importeSinImpuestos": 8263.64,
                           "percepciones":
                                        [{
						"codigoAlicuota": 11,
						"codigoPercepcion": "",
						"porcentaje": 10.50,
						"base": 9999.00,
						"importe": 1049.90
					} ,{
						"codigoAlicuota": 73,
						"codigoPercepcion": "",
						"porcentaje": 3.00,
						"base": 8263.64,
						"importe": 247.91
                                        	}
                                	]
                        	}
                     ,{
				                        "codigo": "100424",
				                        "descripcion": "DELINEADOR RET.CEJAS SK LL 01 1/100424-7",
                                        "descripcionAdicional": "1/100424-7",
				                        "descargaStock" : false,
				                        "cantidad": 1,
                                        "importeIva": 1475.03,
				                        "codigoDeposito": "1",
				                        "codigoUM": "UNI",
				                        "precio": 8499.00,
                                        "importe": 8499.00,
                                         "importeSinImpuestos": 7023.97,
                           "percepciones":
                                        [{
						"codigoAlicuota": 11,
						"codigoPercepcion": "",
						"porcentaje": 10.50,
						"base": 8499.00,
						"importe": 892.40
					} ,{
						"codigoAlicuota": 73,
						"codigoPercepcion": "",
						"porcentaje": 3.00,
						"base": 7023.97,
						"importe": 210.72
                                        	}
                                	]
                        	}
                     ,{
				                        "codigo": "101604",
				                        "descripcion": "MILK EMULS.CORP. EXTRACTO PEPI1/101604-5",
                                        "descripcionAdicional": "1/101604-5",
				                        "descargaStock" : false,
				                        "cantidad": 1,
                                        "importeIva": 1214.70,
				                        "codigoDeposito": "1",
				                        "codigoUM": "UNI",
				                        "precio": 6999.00,
                                        "importe": 6999.00,
                                         "importeSinImpuestos": 5784.30,
                           "percepciones":
                                        [{
						"codigoAlicuota": 11,
						"codigoPercepcion": "",
						"porcentaje": 10.50,
						"base": 6999.00,
						"importe": 734.90
					} ,{
						"codigoAlicuota": 73,
						"codigoPercepcion": "",
						"porcentaje": 3.00,
						"base": 5784.30,
						"importe": 173.53
                                        	}
                                	]
                        	}
                     ,{
				                        "codigo": "100256",
				                        "descripcion": "EAUTOILETTEFEM.FLY50ML1/100256-7",
                                        "descripcionAdicional": "1/100256-7",
				                        "descargaStock" : false,
				                        "cantidad": 1,
                                        "importeIva": 2776.69,
				                        "codigoDeposito": "1",
				                        "codigoUM": "UNI",
				                        "precio": 15999.00,
                                        "importe": 15999.00,
                                         "importeSinImpuestos": 13222.31,
                           "percepciones":
                                        [{
						"codigoAlicuota": 11,
						"codigoPercepcion": "",
						"porcentaje": 10.50,
						"base": 15999.00,
						"importe": 1679.90
					} ,{
						"codigoAlicuota": 73,
						"codigoPercepcion": "",
						"porcentaje": 3.00,
						"base": 13222.31,
						"importe": 396.67
                                        	}
                                	]
                        	}
                     ,{
				                        "codigo": "101605",
				                        "descripcion": "MILK EMULS.CORP. JENGIBRE Y DE1/101605-8",
                                        "descripcionAdicional": "1/101605-8",
				                        "descargaStock" : false,
				                        "cantidad": 1,
                                        "importeIva": 1214.70,
				                        "codigoDeposito": "1",
				                        "codigoUM": "UNI",
				                        "precio": 6999.00,
                                        "importe": 6999.00,
                                         "importeSinImpuestos": 5784.30,
                           "percepciones":
                                        [{
						"codigoAlicuota": 11,
						"codigoPercepcion": "",
						"porcentaje": 10.50,
						"base": 6999.00,
						"importe": 734.90
					} ,{
						"codigoAlicuota": 73,
						"codigoPercepcion": "",
						"porcentaje": 3.00,
						"base": 5784.30,
						"importe": 173.53
                                        	}
                                	]
                        	}
                     ,{
				                        "codigo": "24206",
				                        "descripcion": "MAQUILLAJE CORREC.POTE SK LL 01/24206-4",
                                        "descripcionAdicional": "1/24206-4",
				                        "descargaStock" : false,
				                        "cantidad": 1,
                                        "importeIva": 1388.26,
				                        "codigoDeposito": "1",
				                        "codigoUM": "UNI",
				                        "precio": 7999.00,
                                        "importe": 7999.00,
                                         "importeSinImpuestos": 6610.74,
                           "percepciones":
                                        [{
						"codigoAlicuota": 11,
						"codigoPercepcion": "",
						"porcentaje": 10.50,
						"base": 7999.00,
						"importe": 839.90
					} ,{
						"codigoAlicuota": 73,
						"codigoPercepcion": "",
						"porcentaje": 3.00,
						"base": 6610.74,
						"importe": 198.32
                                        	}
                                	]
                        	}
                     ,{
				                        "codigo": "53248",
				                        "descripcion": "DESOD.ANTIT.ROLLON 55ML CAPRIC1/53248-3",
                                        "descripcionAdicional": "1/53248-3",
				                        "descargaStock" : false,
				                        "cantidad": 1,
                                        "importeIva": 1214.70,
				                        "codigoDeposito": "1",
				                        "codigoUM": "UNI",
				                        "precio": 6999.00,
                                        "importe": 6999.00,
                                         "importeSinImpuestos": 5784.30,
                           "percepciones":
                                        [{
						"codigoAlicuota": 11,
						"codigoPercepcion": "",
						"porcentaje": 10.50,
						"base": 6999.00,
						"importe": 734.90
					} ,{
						"codigoAlicuota": 73,
						"codigoPercepcion": "",
						"porcentaje": 3.00,
						"base": 5784.30,
						"importe": 173.53
                                        	}
                                	]
                        	}
                     ,{
				                        "codigo": "53253",
				                        "descripcion": "DESOD.ANTIT.ROLLON 55ML SEX FO1/53253-6",
                                        "descripcionAdicional": "1/53253-6",
				                        "descargaStock" : false,
				                        "cantidad": 1,
                                        "importeIva": 1041.15,
				                        "codigoDeposito": "1",
				                        "codigoUM": "UNI",
				                        "precio": 5999.00,
                                        "importe": 5999.00,
                                         "importeSinImpuestos": 4957.85,
                           "percepciones":
                                        [{
						"codigoAlicuota": 11,
						"codigoPercepcion": "",
						"porcentaje": 10.50,
						"base": 5999.00,
						"importe": 629.90
					} ,{
						"codigoAlicuota": 73,
						"codigoPercepcion": "",
						"porcentaje": 3.00,
						"base": 4957.85,
						"importe": 148.74
                                        	}
                                	]
                        	}
                     ,{
				                        "codigo": "100852",
				                        "descripcion": "AH+ BRUMA HIDRAT.C/ACIDO HIALU1/100852-1",
                                        "descripcionAdicional": "1/100852-1",
				                        "descargaStock" : false,
				                        "cantidad": 1,
                                        "importeIva": 1475.03,
				                        "codigoDeposito": "1",
				                        "codigoUM": "UNI",
				                        "precio": 8499.00,
                                        "importe": 8499.00,
                                         "importeSinImpuestos": 7023.97,
                           "percepciones":
                                        [{
						"codigoAlicuota": 11,
						"codigoPercepcion": "",
						"porcentaje": 10.50,
						"base": 8499.00,
						"importe": 892.40
					} ,{
						"codigoAlicuota": 73,
						"codigoPercepcion": "",
						"porcentaje": 3.00,
						"base": 7023.97,
						"importe": 210.72
                                        	}
                                	]
                        	}
                     ,{
				                        "codigo": "100721",
				                        "descripcion": "DERMATOLOGY SUERO ANTIEDAD HYA1/100721-7",
                                        "descripcionAdicional": "1/100721-7",
				                        "descargaStock" : false,
				                        "cantidad": 1,
                                        "importeIva": 2603.13,
				                        "codigoDeposito": "1",
				                        "codigoUM": "UNI",
				                        "precio": 14999.00,
                                        "importe": 14999.00,
                                         "importeSinImpuestos": 12395.87,
                           "percepciones":
                                        [{
						"codigoAlicuota": 11,
						"codigoPercepcion": "",
						"porcentaje": 10.50,
						"base": 14999.00,
						"importe": 1574.90
					} ,{
						"codigoAlicuota": 73,
						"codigoPercepcion": "",
						"porcentaje": 3.00,
						"base": 12395.87,
						"importe": 371.88
                                        	}
                                	]
                        	}
                     ,{
				                        "codigo": "101574",
				                        "descripcion": "DESOD.ANTIT.ROLLON 55ML PARAIS1/101574-7",
                                        "descripcionAdicional": "1/101574-7",
				                        "descargaStock" : false,
				                        "cantidad": 2,
                                        "importeIva": 2429.41,
				                        "codigoDeposito": "1",
				                        "codigoUM": "UNI",
				                        "precio": 6999.00,
                                        "importe": 13998.00,
                                         "importeSinImpuestos": 11568.60,
                           "percepciones":
                                        [{
						"codigoAlicuota": 11,
						"codigoPercepcion": "",
						"porcentaje": 10.50,
						"base": 13998.00,
						"importe": 1469.79
					} ,{
						"codigoAlicuota": 73,
						"codigoPercepcion": "",
						"porcentaje": 3.00,
						"base": 11568.60,
						"importe": 347.06
                                        	}
                                	]
                        	}
                     ,{
				                        "codigo": "101405",
				                        "descripcion": "SPLASH HUMECT. B.LOVE COCONUT 4/101405-0",
                                        "descripcionAdicional": "4/101405-0",
				                        "descargaStock" : false,
				                        "cantidad": 1,
                                        "importeIva": 0.00,
				                        "codigoDeposito": "1",
				                        "codigoUM": "UNI",
				                        "precio": 0.01,
                                        "importe": 0.01,
                                         "importeSinImpuestos": 0.01,
                           "percepciones":
                                        [{
						"codigoAlicuota": 11,
						"codigoPercepcion": "",
						"porcentaje": 10.50,
						"base": 0.01,
						"importe": 0.00
					} ,{
						"codigoAlicuota": 73,
						"codigoPercepcion": "",
						"porcentaje": 3.00,
						"base": 0.01,
						"importe": 0.00
                                        	}
                                	]
                        	}
                     ,{
	"codigo": "03",
	"descripcion": "Bonificacion Cosméticos",
	"descargaStock" : false,
	"cantidad": -1,
	"codigoDeposito": "1",
        "importeIva": -9594.48,
	"codigoUM": "BON",
	"precio": 55282.50,
        "importe": 55282.50,
        "importeSinImpuestos": -45688.02,"percepciones":
                                        [{
						"codigoAlicuota": 11,
						"codigoPercepcion": "",
						"porcentaje" : 10.50,
						"base": -55282.50,
						"importe": -5804.66
					} ,{
						"codigoAlicuota": 73,
						"codigoPercepcion": "",
						"porcentaje": 3.00,
						"base": -45688.02,
						"importe": -1370.64
                                        	}
                                	]
        },{
				"codigo": "04",
				"descripcion": "Bonificación Practicosas",
				"descargaStock" : false,
				"cantidad": -1,
				"codigoDeposito": "1",
                                "importeIva": -78.07,
				"codigoUM": "BON",
				"precio": 449.85,
                                "importe": 449.85,
                                "importeSinImpuestos": -371.78,"percepciones":
                                        [{
						"codigoAlicuota": 11,
						"codigoPercepcion": "",
						"porcentaje" : 10.50,
						"base": -449.85,
						"importe": -47.23
					} ,{
						"codigoAlicuota": 73,
						"codigoPercepcion": "",
						"porcentaje": 3.00,
						"base": -371.78,
						"importe": -11.15
                                        	}
                                	]
                        	},
                                
                     {
				"codigo": "02",
				"descripcion": "Gastos administrativos",
				"descargaStock" : false,
				"cantidad": 1,
				"codigoDeposito": "1",
                                "importeIva": 675.75,
				"codigoUM": "UNI",
				"precio": 3893.63,
                                "importe": 3893.63,
                                "importeSinImpuestos": 3217.88,"percepciones":
                                        [{
						"codigoAlicuota": 11,
						"codigoPercepcion": "",
						"porcentaje" : 10.50,
						"base": 3893.63,
						"importe": 408.83
					} ,{
						"codigoAlicuota": 73,
						"codigoPercepcion": "",
						"porcentaje": 3.00,
						"base": 3217.88,
						"importe": 96.54
                                        	}
                                	]
                        	}
                     
		],
		"cuotasCuentaCorriente" :
		[
			{
				"fechaVencimiento": "2026-03-18 00:00:00.000",
				"importe" : 153014.02
			}
                        ]
            }
        ]