

        [
	{
		"codigoTipoComprobante": "FAC",
		"numeroComprobante": "E0001100000089",
		"codigoTalonario": "22",
		"codigoCliente": "57513",
		"codigoCondicionDeVenta": 1,
		"numeroDeProyecto": "",
		"codigoOperacionRG3685": "00001",
		"codigoClasificacion": "",
		"fechaComprobante": "2026-03-18 00:00:00.000",
		"fechaCierreTesoreria": "2026-03-18 00:00:00.000",
		"codigoListaPrecio": 2,
		"cotizacionVentas": null,
		"codigoContracuenta": "20",
		"codigoDeposito": "1",
		"codigoVendedor": "123",
		"idMotivo": "3",
		"codigoAsiento": "1",
		"leyenda1": "",
		"leyenda2": "",
		"leyenda3": "",
		"leyenda4": "",
		"leyenda5": "",
		"esMonedaExtranjera": false,
		"total" : 330545.22,
		"totalExento": 330545.22,
		"totalIva": 0.00,
		"subtotal": 330545.22,
		"totalSinImpuestos": 0.00,
		"subtotalSinImpuestos": 0.00,
		"descuentoPorcentaje": 0,
		"descuentoMonto": 0,
		"descuentoMontoSinIva": 0,
		"recargoPorcentaje": 0,
		"recargoMonto": 0,
		"recargoMontoSinIva": 0,
		"recargoFletePorcentaje": 0,
		"recargoFleteMonto": 0,
		"recargoFleteMontoSinIva": 0,
		"interesesPorcentaje": 0.00,
		"interesesMontoSinIva": 0.00,
		"observaciones": "",
		"rg3668TipoIdentificacionFirmante": null,
		"rg3668CaracterDelFirmante": null,
		"rg3668CodigoIdentificacionFirmante": "",
		"rg3668MotivoDeExcepcion": null,
		"rg3668CodigoWeb": "666",
		"items": [
                {
				    "codigo": "100062",
                    "descripcion": "THERMO EXPERT PROTEC.TERMICO I",
                    "descripcionAdicional": "                \r\n-",
				    "codigoDeposito": "1",
                    "codigoTasaIva": "3",
				    "cantidad": 2,
				    "precio": 9999.00,
                    "importe": 19998.00
                        	}
                     ,{
				    "codigo": "100425",
                    "descripcion": "DELINEADOR RET. CEJAS SK LL 02",
                    "descripcionAdicional": "                \r\n-",
				    "codigoDeposito": "1",
                    "codigoTasaIva": "3",
				    "cantidad": 1,
				    "precio": 8499.00,
                    "importe": 8499.00
                        	}
                     ,{
				    "codigo": "100459",
                    "descripcion": "LOCION COLONIA FEMENINA ADDICT",
                    "descripcionAdicional": "                \r\n-",
				    "codigoDeposito": "1",
                    "codigoTasaIva": "3",
				    "cantidad": 1,
				    "precio": 6999.00,
                    "importe": 6999.00
                        	}
                     ,{
				    "codigo": "100727",
                    "descripcion": "ESMALTE P/UNAS YOU 06 NEGRO CH",
                    "descripcionAdicional": "                \r\n-",
				    "codigoDeposito": "1",
                    "codigoTasaIva": "3",
				    "cantidad": 1,
				    "precio": 1849.00,
                    "importe": 1849.00
                        	}
                     ,{
				    "codigo": "100773",
                    "descripcion": "MAQUILLAJE CORRECTOR YOU N02 M",
                    "descripcionAdicional": "                \r\n-",
				    "codigoDeposito": "1",
                    "codigoTasaIva": "3",
				    "cantidad": 2,
				    "precio": 4999.00,
                    "importe": 9998.00
                        	}
                     ,{
				    "codigo": "100801",
                    "descripcion": "EAU TOILETTE FEM. MAGIC LOVE 5",
                    "descripcionAdicional": "                \r\n-",
				    "codigoDeposito": "1",
                    "codigoTasaIva": "3",
				    "cantidad": 2,
				    "precio": 15999.00,
                    "importe": 31998.00
                        	}
                     ,{
				    "codigo": "100909",
                    "descripcion": "ESMALTE P/UNAS YOU 09 VERDE ZE",
                    "descripcionAdicional": "                \r\n-",
				    "codigoDeposito": "1",
                    "codigoTasaIva": "3",
				    "cantidad": 1,
				    "precio": 1849.00,
                    "importe": 1849.00
                        	}
                     ,{
				    "codigo": "101000",
                    "descripcion": "DESODORANTE ANTIT. ROLLON BE V",
                    "descripcionAdicional": "                \r\n-",
				    "codigoDeposito": "1",
                    "codigoTasaIva": "3",
				    "cantidad": 2,
				    "precio": 7999.00,
                    "importe": 15998.00
                        	}
                     ,{
				    "codigo": "101052",
                    "descripcion": "EAU TOILETTE MASC. NIGHT SEDUC",
                    "descripcionAdicional": "                \r\n-",
				    "codigoDeposito": "1",
                    "codigoTasaIva": "3",
				    "cantidad": 2,
				    "precio": 19999.00,
                    "importe": 39998.00
                        	}
                     ,{
				    "codigo": "101061",
                    "descripcion": "DELINEADOR P/OJOS 18CM 01 NEGR",
                    "descripcionAdicional": "                \r\n-",
				    "codigoDeposito": "1",
                    "codigoTasaIva": "3",
				    "cantidad": 2,
				    "precio": 2599.00,
                    "importe": 5198.00
                        	}
                     ,{
				    "codigo": "101063",
                    "descripcion": "DELINEADOR P/OJOS 18CM 03 AZUL",
                    "descripcionAdicional": "                \r\n-",
				    "codigoDeposito": "1",
                    "codigoTasaIva": "3",
				    "cantidad": 2,
				    "precio": 2599.00,
                    "importe": 5198.00
                        	}
                     ,{
				    "codigo": "101067",
                    "descripcion": "DELINEADOR P/OJOS 18CM 07 CELE",
                    "descripcionAdicional": "                \r\n-",
				    "codigoDeposito": "1",
                    "codigoTasaIva": "3",
				    "cantidad": 2,
				    "precio": 2599.00,
                    "importe": 5198.00
                        	}
                     ,{
				    "codigo": "101076",
                    "descripcion": "DELINEADOR P/LABIOS 18CM 05 NU",
                    "descripcionAdicional": "                \r\n-",
				    "codigoDeposito": "1",
                    "codigoTasaIva": "3",
				    "cantidad": 1,
				    "precio": 2599.00,
                    "importe": 2599.00
                        	}
                     ,{
				    "codigo": "101132",
                    "descripcion": "CREMA PARA CUERPO BE VEGAN 300",
                    "descripcionAdicional": "                \r\n-",
				    "codigoDeposito": "1",
                    "codigoTasaIva": "3",
				    "cantidad": 2,
				    "precio": 12999.00,
                    "importe": 25998.00
                        	}
                     ,{
				    "codigo": "101259",
                    "descripcion": "ESMALTE P/UNAS YOU 15 AZUL ROY",
                    "descripcionAdicional": "                \r\n-",
				    "codigoDeposito": "1",
                    "codigoTasaIva": "3",
				    "cantidad": 1,
				    "precio": 1849.00,
                    "importe": 1849.00
                        	}
                     ,{
				    "codigo": "101285",
                    "descripcion": "LOCION COLONIA FEMENINA MAGNET",
                    "descripcionAdicional": "                \r\n-",
				    "codigoDeposito": "1",
                    "codigoTasaIva": "3",
				    "cantidad": 2,
				    "precio": 6999.00,
                    "importe": 13998.00
                        	}
                     ,{
				    "codigo": "101290",
                    "descripcion": "EAU PARFUM.MASC. SUPREME 100ML",
                    "descripcionAdicional": "                \r\n-",
				    "codigoDeposito": "1",
                    "codigoTasaIva": "3",
				    "cantidad": 2,
				    "precio": 22999.00,
                    "importe": 45998.00
                        	}
                     ,{
				    "codigo": "101379",
                    "descripcion": "SK SOMBRAS COMPACTAS X 12 Nº ",
                    "descripcionAdicional": "                \r\n23001IC06023971Z-BUE",
				    "codigoDeposito": "1",
                    "codigoTasaIva": "3",
				    "cantidad": 2,
				    "precio": 24999.00,
                    "importe": 49998.00
                        	}
                     ,{
				    "codigo": "101422",
                    "descripcion": "EAU TOILETTE MASC. CONNECTION ",
                    "descripcionAdicional": "                \r\n-",
				    "codigoDeposito": "1",
                    "codigoTasaIva": "3",
				    "cantidad": 2,
				    "precio": 19999.00,
                    "importe": 39998.00
                        	}
                     ,{
				    "codigo": "101431",
                    "descripcion": "ESMALTE YOU HOLOSHINE 1 ROSA D",
                    "descripcionAdicional": "                \r\n-",
				    "codigoDeposito": "1",
                    "codigoTasaIva": "3",
				    "cantidad": 1,
				    "precio": 1849.00,
                    "importe": 1849.00
                        	}
                     ,{
				    "codigo": "101432",
                    "descripcion": "ESMALTE YOU HOLOSHINE 2 CELEST",
                    "descripcionAdicional": "                \r\n-",
				    "codigoDeposito": "1",
                    "codigoTasaIva": "3",
				    "cantidad": 1,
				    "precio": 1849.00,
                    "importe": 1849.00
                        	}
                     ,{
				    "codigo": "101495",
                    "descripcion": "PROTECT INSTA DRY ACEITE SEC.R",
                    "descripcionAdicional": "                \r\n-",
				    "codigoDeposito": "1",
                    "codigoTasaIva": "3",
				    "cantidad": 3,
				    "precio": 3999.00,
                    "importe": 11997.00
                        	}
                     ,{
				    "codigo": "101570",
                    "descripcion": "ESMALTE P/UNAS YOU 19 FANTASY ",
                    "descripcionAdicional": "                \r\n-",
				    "codigoDeposito": "1",
                    "codigoTasaIva": "3",
				    "cantidad": 1,
				    "precio": 1849.00,
                    "importe": 1849.00
                        	}
                     ,{
				    "codigo": "204946",
                    "descripcion": "SCRUNCHIE RASO GIULIANA S/E CO",
                    "descripcionAdicional": "                \r\n-",
				    "codigoDeposito": "1",
                    "codigoTasaIva": "3",
				    "cantidad": 2,
				    "precio": 2999.00,
                    "importe": 5998.00
                        	}
                     ,{
				    "codigo": "21311",
                    "descripcion": "PROTECT QUITAESM.HUMECTO NUTRI",
                    "descripcionAdicional": "                \r\n-",
				    "codigoDeposito": "1",
                    "codigoTasaIva": "3",
				    "cantidad": 2,
				    "precio": 6999.00,
                    "importe": 13998.00
                        	}
                     ,{
				    "codigo": "260",
                    "descripcion": "FOLLETO CAMP. 11              ",
                    "descripcionAdicional": "                \r\n-",
				    "codigoDeposito": "1",
                    "codigoTasaIva": "3",
				    "cantidad": 2,
				    "precio": 0.01,
                    "importe": 0.02
                        	}
                     ,{
				    "codigo": "403570",
                    "descripcion": "EXPRIMIDOR MANUAL STAR CUISINE",
                    "descripcionAdicional": "                \r\n21001IC04254485S-BUE",
				    "codigoDeposito": "1",
                    "codigoTasaIva": "3",
				    "cantidad": 2,
				    "precio": 8999.00,
                    "importe": 17998.00
                        	}
                     ,{
				    "codigo": "404185",
                    "descripcion": "SET X 6 RESALTADORES DULL     ",
                    "descripcionAdicional": "                \r\n-",
				    "codigoDeposito": "1",
                    "codigoTasaIva": "3",
				    "cantidad": 1,
				    "precio": 7999.00,
                    "importe": 7999.00
                        	}
                     ,{
				    "codigo": "406090",
                    "descripcion": "CARTUCHERA FRUTTI             ",
                    "descripcionAdicional": "                \r\n24001IC04007004E-BUE",
				    "codigoDeposito": "1",
                    "codigoTasaIva": "3",
				    "cantidad": 1,
				    "precio": 6999.00,
                    "importe": 6999.00
                        	}
                     ,{
				    "codigo": "407148",
                    "descripcion": "AURICULARES C/BLUETOOTH S/E CO",
                    "descripcionAdicional": "                \r\n-",
				    "codigoDeposito": "1",
                    "codigoTasaIva": "3",
				    "cantidad": 1,
				    "precio": 29999.00,
                    "importe": 29999.00
                        	}
                     ,{
				    "codigo": "407347",
                    "descripcion": "BOWL C/TAPA DINA BCO 500CC    ",
                    "descripcionAdicional": "                \r\n-",
				    "codigoDeposito": "1",
                    "codigoTasaIva": "3",
				    "cantidad": 2,
				    "precio": 2499.00,
                    "importe": 4998.00
                        	}
                     ,{
				    "codigo": "407348",
                    "descripcion": "BOWL C/TAPA DINA CEL 500CC    ",
                    "descripcionAdicional": "                \r\n-",
				    "codigoDeposito": "1",
                    "codigoTasaIva": "3",
				    "cantidad": 2,
				    "precio": 2499.00,
                    "importe": 4998.00
                        	}
                     ,{
				    "codigo": "407349",
                    "descripcion": "BOWL C/TAPA DINA ROSA 500CC   ",
                    "descripcionAdicional": "                \r\n-",
				    "codigoDeposito": "1",
                    "codigoTasaIva": "3",
				    "cantidad": 2,
				    "precio": 2499.00,
                    "importe": 4998.00
                        	}
                     ,{
				    "codigo": "43243",
                    "descripcion": "EAU TOILETTE MASC. RED HELL 55",
                    "descripcionAdicional": "                \r\n-",
				    "codigoDeposito": "1",
                    "codigoTasaIva": "3",
				    "cantidad": 2,
				    "precio": 17999.00,
                    "importe": 35998.00
                        	}
                     ,{
				    "codigo": "500712",
                    "descripcion": "NUEVOS CLIENTES C11-2025      ",
                    "descripcionAdicional": "                \r\n-",
				    "codigoDeposito": "1",
                    "codigoTasaIva": "3",
				    "cantidad": 1,
				    "precio": 0.01,
                    "importe": 0.01
                        	}
                     ,{
				    "codigo": "500716",
                    "descripcion": "VOLANTE EQUAL                 ",
                    "descripcionAdicional": "                \r\n-",
				    "codigoDeposito": "1",
                    "codigoTasaIva": "3",
				    "cantidad": 1,
				    "precio": 0.01,
                    "importe": 0.01
                        	}
                     ,{
				    "codigo": "900784",
                    "descripcion": "PR.RELOJP/DAMALIBERTY         ",
                    "descripcionAdicional": "                \r\n22073IC04139270W-EZE",
				    "codigoDeposito": "1",
                    "codigoTasaIva": "3",
				    "cantidad": 1,
				    "precio": 19999.00,
                    "importe": 19999.00
                        	}
                     ,{
	"codigo": "03",
	"descripcion": "Bonificacion Cosméticos",
	"codigoDeposito": "1",
        "codigoTasaIva": "3",
	"cantidad": -1,
	"precio": 160303.20,
        "importe": 160303.20
        },{
	"codigo": "04",
	"descripcion": "Bonificación Practicosas",
	"codigoDeposito": "1",
        "codigoTasaIva": "3",
	"cantidad": -1,
	"precio": 25996.50,
        "importe": 25996.50
        },{
	"codigo": "02",
        "descripcion": "Gastos administrativos",
	"codigoDeposito": "1",
        "codigoTasaIva": "3",
	"cantidad": 1,
	"precio": 12100.88,
        "importe": 12100.88
        },
		],
		"cuotasCuentaCorriente" :
		[
			{
				"fechaVencimiento": "2026-03-18 00:00:00.000",
				"importe" : 330545.22
			}
                        ],
            "xmlTyp" : "",
            "CuitDestino": "J",
            "TipoExpo": "4",
            "PaisAfip": "200",
            "CodigoIncoterms": "FOB",
            "DescripcionIncoterms": ""  
            }
        ]